odoo/addons/l10n_ro_message_spv/README.rst
odoo/addons/l10n_ro_message_spv/__init__.py
odoo/addons/l10n_ro_message_spv/__manifest__.py
odoo/addons/l10n_ro_message_spv/data/ir_cron_data.xml
odoo/addons/l10n_ro_message_spv/i18n/l10n_ro_message_spv.pot
odoo/addons/l10n_ro_message_spv/i18n/ro.po
odoo/addons/l10n_ro_message_spv/models/__init__.py
odoo/addons/l10n_ro_message_spv/models/message_spv.py
odoo/addons/l10n_ro_message_spv/models/res_company.py
odoo/addons/l10n_ro_message_spv/readme/CONFIGURE.rst
odoo/addons/l10n_ro_message_spv/readme/CONTRIBUTORS.rst
odoo/addons/l10n_ro_message_spv/readme/DESCRIPTION.rst
odoo/addons/l10n_ro_message_spv/security/ir.model.access.csv
odoo/addons/l10n_ro_message_spv/security/security.xml
odoo/addons/l10n_ro_message_spv/static/description/icon.png
odoo/addons/l10n_ro_message_spv/static/description/icon.svg
odoo/addons/l10n_ro_message_spv/static/description/index.html
odoo/addons/l10n_ro_message_spv/static/src/js/message_spv.js
odoo/addons/l10n_ro_message_spv/static/src/xml/message_spv.xml
odoo/addons/l10n_ro_message_spv/tests/__init__.py
odoo/addons/l10n_ro_message_spv/tests/test_message_spv.py
odoo/addons/l10n_ro_message_spv/views/assets.xml
odoo/addons/l10n_ro_message_spv/views/message_spv_view.xml
odoo14_addon_l10n_ro_message_spv-14.0.1.1.2.dev3.dist-info/METADATA
odoo14_addon_l10n_ro_message_spv-14.0.1.1.2.dev3.dist-info/WHEEL
odoo14_addon_l10n_ro_message_spv-14.0.1.1.2.dev3.dist-info/top_level.txt
odoo14_addon_l10n_ro_message_spv-14.0.1.1.2.dev3.dist-info/RECORD
