Metadata-Version: 2.1
Name: odoo14-addon-l10n_ro_message_spv
Version: 14.0.1.1.2.dev3
Summary: Romania - Mesaje SPV
Home-page: https://github.com/OCA/l10n-romania
Author: Terrabit,NextERP Romania,Odoo Community Association (OCA)
Author-email: support@odoo-community.org
License: AGPL-3
Classifier: Programming Language :: Python
Classifier: Framework :: Odoo
Classifier: Framework :: Odoo :: 14.0
Classifier: License :: OSI Approved :: GNU Affero General Public License v3
Classifier: Development Status :: 4 - Beta
Requires-Python: >=3.6
Requires-Dist: odoo14-addon-l10n-ro-account-anaf-sync
Requires-Dist: odoo14-addon-l10n-ro-account-edi-ubl
Requires-Dist: odoo <14.1dev,>=14.0a
